setup.py
micropython_redis.set.egg-info/PKG-INFO
micropython_redis.set.egg-info/SOURCES.txt
micropython_redis.set.egg-info/dependency_links.txt
micropython_redis.set.egg-info/requires.txt
micropython_redis.set.egg-info/top_level.txt
micropython_redis.set.egg-info/zip-safe
uredis_modular/set.py